Python_Peatio/Accounts.py
Python_Peatio/Auth.py
Python_Peatio/Market.py
Python_Peatio/UserAPI_Markets.py
Python_Peatio/UserAPI_Public.py
Python_Peatio/__init__.py
Python_Peatio-1.4.0.dist-info/METADATA
Python_Peatio-1.4.0.dist-info/WHEEL
Python_Peatio-1.4.0.dist-info/top_level.txt
Python_Peatio-1.4.0.dist-info/RECORD
