Metadata-Version: 2.1
Name: Python-Peatio
Version: 1.4.0
Summary: Python Package for Openware Peatio Cryptocurrency Exchange & Accounting Software
Home-page: UNKNOWN
Author: Kumar Saurav
Author-email: <kumar@prescient-automation.com>
License: UNKNOWN
Keywords: python,peatio,crypto,crypto currency,open source,exchanges,open source exchange,openware exchange
Platform: UNKNOWN
Classifier: Development Status :: 3 - Alpha
Classifier: Intended Audience :: Developers
Classifier: Programming Language :: Python :: 3
Classifier: Operating System :: Unix
Classifier: Operating System :: MacOS :: MacOS X
Classifier: Operating System :: Microsoft :: Windows
Requires-Dist: python-http-client
